escpos/__init__.py
escpos/constants.py
escpos/pos_barcode.py
escpos/pos_component.py
escpos/pos_config.py
escpos/pos_document.py
escpos/pos_linefeed.py
escpos/pos_printer.py
escpos/pos_printer_interface.py
escpos/pos_printer_mock.py
escpos/pos_qrcode.py
escpos/pos_receipt.py
escpos/pos_special_character.py
escpos/pos_text.py
escpos_python-1.0.0.dist-info/METADATA
escpos_python-1.0.0.dist-info/WHEEL
escpos_python-1.0.0.dist-info/top_level.txt
escpos_python-1.0.0.dist-info/RECORD
