Metadata-Version: 2.4
Name: escpos-python
Version: 1.0.0
Summary: ESC/POS receipt printing library in pure Python
Author-email: Mathis Neunzig <mathis.neunzig@gmail.com>
License-Expression: MIT
Project-URL: Homepage, https://github.com/DrBackmischung/ESCPOS-Python
Classifier: Development Status :: 4 - Beta
Classifier: Intended Audience :: Developers
Classifier: Programming Language :: Python :: 3
Classifier: Programming Language :: Python :: 3.10
Classifier: Operating System :: OS Independent
Requires-Python: >=3.8
